{"nodes": [{"group": 1, "name": 348}, {"group": 2, "name": 509}, {"group": 2, "name": 419}, {"group": 2, "name": 554}, {"group": 2, "name": 469}, {"group": 2, "name": 477}, {"group": 2, "name": 485}, {"group": 2, "name": 516}, {"group": 2, "name": 424}, {"group": 1, "name": 397}, {"group": 2, "name": 551}, {"group": 2, "name": 381}, {"group": 2, "name": 380}, {"group": 2, "name": 518}, {"group": 2, "name": 389}, {"group": 2, "name": 435}, {"group": 2, "name": 505}, {"group": 2, "name": 563}, {"group": 2, "name": 459}, {"group": 2, "name": 486}, {"group": 2, "name": 457}, {"group": 2, "name": 357}, {"group": 3, "name": 526}, {"group": 3, "name": 449}, {"group": 3, "name": 412}, {"group": 3, "name": 489}, {"group": 3, "name": 475}, {"group": 3, "name": 396}, {"group": 3, "name": 458}, {"group": 3, "name": 533}, {"group": 3, "name": 438}, {"group": 3, "name": 568}, {"group": 3, "name": 388}, {"group": 3, "name": 361}, {"group": 3, "name": 528}, {"group": 3, "name": 553}, {"group": 3, "name": 565}, {"group": 3, "name": 514}, {"group": 3, "name": 558}, {"group": 3, "name": 497}, {"group": 3, "name": 432}, {"group": 3, "name": 504}, {"group": 3, "name": 354}, {"group": 3, "name": 547}, {"group": 3, "name": 463}, {"group": 3, "name": 506}, {"group": 3, "name": 544}, {"group": 3, "name": 481}, {"group": 3, "name": 372}, {"group": 3, "name": 519}, {"group": 3, "name": 570}, {"group": 3, "name": 355}, {"group": 3, "name": 390}, {"group": 3, "name": 363}, {"group": 3, "name": 402}, {"group": 3, "name": 566}, {"group": 3, "name": 470}, {"group": 3, "name": 450}, {"group": 3, "name": 500}, {"group": 3, "name": 367}, {"group": 3, "name": 482}, {"group": 3, "name": 452}, {"group": 3, "name": 521}, {"group": 3, "name": 510}, {"group": 3, "name": 360}, {"group": 3, "name": 555}, {"group": 3, "name": 455}, {"group": 3, "name": 548}, {"group": 3, "name": 460}, {"group": 3, "name": 531}, {"group": 3, "name": 488}, {"group": 3, "name": 543}, {"group": 3, "name": 530}, {"group": 3, "name": 557}, {"group": 3, "name": 359}, {"group": 3, "name": 523}, {"group": 3, "name": 403}, {"group": 3, "name": 410}, {"group": 3, "name": 507}, {"group": 3, "name": 474}, {"group": 3, "name": 374}, {"group": 3, "name": 545}, {"group": 3, "name": 496}, {"group": 3, "name": 515}, {"group": 3, "name": 480}, {"group": 3, "name": 541}, {"group": 3, "name": 376}, {"group": 3, "name": 546}, {"group": 3, "name": 370}, {"group": 3, "name": 418}, {"group": 3, "name": 382}, {"group": 3, "name": 562}, {"group": 3, "name": 444}], "links": [{"source": 0, "target": 1}, {"source": 0, "target": 2}, {"source": 0, "target": 3}, {"source": 0, "target": 4}, {"source": 0, "target": 5}, {"source": 0, "target": 6}, {"source": 0, "target": 7}, {"source": 0, "target": 8}, {"source": 0, "target": 9}, {"source": 0, "target": 10}, {"source": 0, "target": 11}, {"source": 0, "target": 12}, {"source": 0, "target": 13}, {"source": 0, "target": 14}, {"source": 0, "target": 15}, {"source": 0, "target": 16}, {"source": 0, "target": 17}, {"source": 0, "target": 18}, {"source": 0, "target": 19}, {"source": 0, "target": 20}, {"source": 0, "target": 21}, {"source": 0, "target": 22}, {"source": 0, "target": 23}, {"source": 0, "target": 24}, {"source": 0, "target": 25}, {"source": 0, "target": 26}, {"source": 0, "target": 27}, {"source": 0, "target": 28}, {"source": 0, "target": 29}, {"source": 0, "target": 30}, {"source": 0, "target": 31}, {"source": 0, "target": 32}, {"source": 0, "target": 33}, {"source": 0, "target": 34}, {"source": 0, "target": 35}, {"source": 0, "target": 36}, {"source": 0, "target": 37}, {"source": 0, "target": 38}, {"source": 0, "target": 39}, {"source": 0, "target": 40}, {"source": 0, "target": 41}, {"source": 0, "target": 42}, {"source": 0, "target": 43}, {"source": 0, "target": 44}, {"source": 0, "target": 45}, {"source": 0, "target": 46}, {"source": 0, "target": 47}, {"source": 0, "target": 48}, {"source": 0, "target": 49}, {"source": 0, "target": 50}, {"source": 0, "target": 51}, {"source": 0, "target": 52}, {"source": 0, "target": 53}, {"source": 0, "target": 54}, {"source": 0, "target": 55}, {"source": 0, "target": 56}, {"source": 0, "target": 57}, {"source": 0, "target": 58}, {"source": 0, "target": 59}, {"source": 0, "target": 60}, {"source": 0, "target": 61}, {"source": 0, "target": 62}, {"source": 0, "target": 63}, {"source": 0, "target": 64}, {"source": 0, "target": 65}, {"source": 0, "target": 66}, {"source": 0, "target": 67}, {"source": 0, "target": 68}, {"source": 0, "target": 69}, {"source": 0, "target": 70}, {"source": 0, "target": 71}, {"source": 0, "target": 72}, {"source": 0, "target": 73}, {"source": 0, "target": 74}, {"source": 0, "target": 75}, {"source": 0, "target": 76}, {"source": 0, "target": 77}, {"source": 0, "target": 78}, {"source": 0, "target": 79}, {"source": 0, "target": 80}, {"source": 0, "target": 81}, {"source": 0, "target": 82}, {"source": 0, "target": 83}, {"source": 0, "target": 84}, {"source": 0, "target": 85}, {"source": 0, "target": 86}, {"source": 0, "target": 87}, {"source": 0, "target": 88}, {"source": 0, "target": 89}, {"source": 0, "target": 90}, {"source": 0, "target": 91}, {"source": 0, "target": 92}, {"source": 57, "target": 69}, {"source": 36, "target": 24}, {"source": 87, "target": 43}, {"source": 59, "target": 61}, {"source": 57, "target": 33}, {"source": 61, "target": 74}, {"source": 63, "target": 62}, {"source": 33, "target": 73}, {"source": 86, "target": 65}, {"source": 36, "target": 58}, {"source": 4, "target": 7}, {"source": 89, "target": 45}, {"source": 87, "target": 86}, {"source": 58, "target": 27}, {"source": 20, "target": 5}, {"source": 43, "target": 57}, {"source": 43, "target": 67}, {"source": 90, "target": 61}, {"source": 79, "target": 27}, {"source": 53, "target": 22}, {"source": 33, "target": 74}, {"source": 17, "target": 81}, {"source": 92, "target": 75}, {"source": 26, "target": 78}, {"source": 67, "target": 43}, {"source": 2, "target": 46}, {"source": 67, "target": 65}, {"source": 59, "target": 76}, {"source": 46, "target": 41}, {"source": 17, "target": 46}, {"source": 28, "target": 81}, {"source": 69, "target": 92}, {"source": 68, "target": 83}, {"source": 46, "target": 53}, {"source": 56, "target": 49}, {"source": 65, "target": 41}, {"source": 38, "target": 48}, {"source": 61, "target": 55}, {"source": 26, "target": 89}, {"source": 65, "target": 76}, {"source": 70, "target": 39}, {"source": 83, "target": 80}, {"source": 63, "target": 29}, {"source": 51, "target": 39}, {"source": 44, "target": 32}, {"source": 30, "target": 70}, {"source": 65, "target": 86}, {"source": 86, "target": 2}, {"source": 88, "target": 45}, {"source": 65, "target": 42}, {"source": 68, "target": 71}, {"source": 24, "target": 60}, {"source": 39, "target": 76}, {"source": 45, "target": 17}, {"source": 87, "target": 66}, {"source": 36, "target": 82}, {"source": 54, "target": 28}, {"source": 74, "target": 27}, {"source": 33, "target": 44}, {"source": 8, "target": 20}, {"source": 56, "target": 27}, {"source": 41, "target": 37}, {"source": 54, "target": 88}, {"source": 45, "target": 58}, {"source": 57, "target": 39}, {"source": 17, "target": 21}, {"source": 71, "target": 9}, {"source": 55, "target": 40}, {"source": 46, "target": 62}, {"source": 61, "target": 63}, {"source": 48, "target": 69}, {"source": 32, "target": 24}, {"source": 49, "target": 43}, {"source": 54, "target": 30}, {"source": 58, "target": 87}, {"source": 76, "target": 27}, {"source": 57, "target": 58}, {"source": 10, "target": 11}, {"source": 77, "target": 31}, {"source": 19, "target": 18}, {"source": 24, "target": 51}, {"source": 56, "target": 42}, {"source": 71, "target": 66}, {"source": 89, "target": 24}, {"source": 30, "target": 32}, {"source": 61, "target": 2}, {"source": 37, "target": 64}, {"source": 55, "target": 46}, {"source": 78, "target": 58}, {"source": 61, "target": 39}, {"source": 17, "target": 30}, {"source": 74, "target": 51}, {"source": 86, "target": 75}, {"source": 43, "target": 44}, {"source": 76, "target": 25}, {"source": 39, "target": 14}, {"source": 24, "target": 38}, {"source": 65, "target": 59}, {"source": 80, "target": 45}, {"source": 92, "target": 68}, {"source": 39, "target": 15}, {"source": 88, "target": 65}, {"source": 53, "target": 39}, {"source": 82, "target": 30}, {"source": 58, "target": 69}, {"source": 34, "target": 35}, {"source": 2, "target": 86}, {"source": 53, "target": 24}, {"source": 54, "target": 81}, {"source": 24, "target": 82}, {"source": 83, "target": 24}, {"source": 59, "target": 27}, {"source": 25, "target": 59}, {"source": 76, "target": 51}, {"source": 51, "target": 36}, {"source": 34, "target": 71}, {"source": 75, "target": 86}, {"source": 32, "target": 61}, {"source": 55, "target": 86}, {"source": 13, "target": 12}, {"source": 57, "target": 52}, {"source": 73, "target": 58}, {"source": 80, "target": 54}, {"source": 48, "target": 77}, {"source": 1, "target": 3}, {"source": 23, "target": 78}, {"source": 43, "target": 48}, {"source": 58, "target": 45}, {"source": 39, "target": 66}, {"source": 41, "target": 85}, {"source": 54, "target": 92}, {"source": 38, "target": 81}, {"source": 78, "target": 42}, {"source": 89, "target": 39}, {"source": 32, "target": 39}, {"source": 76, "target": 56}, {"source": 61, "target": 32}, {"source": 59, "target": 65}, {"source": 27, "target": 43}, {"source": 73, "target": 39}, {"source": 85, "target": 66}, {"source": 9, "target": 92}, {"source": 78, "target": 23}, {"source": 22, "target": 80}, {"source": 68, "target": 35}, {"source": 78, "target": 54}, {"source": 69, "target": 33}, {"source": 83, "target": 67}, {"source": 92, "target": 26}, {"source": 75, "target": 46}, {"source": 65, "target": 56}, {"source": 82, "target": 55}, {"source": 19, "target": 1}, {"source": 73, "target": 87}, {"source": 78, "target": 55}, {"source": 60, "target": 45}, {"source": 43, "target": 89}, {"source": 73, "target": 74}, {"source": 84, "target": 71}, {"source": 63, "target": 65}, {"source": 3, "target": 16}, {"source": 65, "target": 88}, {"source": 28, "target": 54}, {"source": 60, "target": 36}, {"source": 80, "target": 75}, {"source": 9, "target": 45}, {"source": 69, "target": 86}, {"source": 25, "target": 73}, {"source": 75, "target": 30}, {"source": 86, "target": 52}, {"source": 38, "target": 24}, {"source": 80, "target": 82}, {"source": 89, "target": 31}, {"source": 69, "target": 41}, {"source": 3, "target": 9}, {"source": 5, "target": 13}, {"source": 61, "target": 44}, {"source": 50, "target": 38}, {"source": 86, "target": 70}, {"source": 75, "target": 92}, {"source": 33, "target": 25}, {"source": 42, "target": 9}, {"source": 44, "target": 33}, {"source": 2, "target": 13}, {"source": 37, "target": 86}, {"source": 43, "target": 41}, {"source": 83, "target": 35}, {"source": 46, "target": 24}, {"source": 58, "target": 32}, {"source": 56, "target": 90}, {"source": 47, "target": 44}, {"source": 15, "target": 39}, {"source": 86, "target": 32}, {"source": 26, "target": 65}, {"source": 64, "target": 78}, {"source": 76, "target": 61}, {"source": 3, "target": 17}, {"source": 43, "target": 47}, {"source": 44, "target": 77}, {"source": 19, "target": 21}, {"source": 45, "target": 60}, {"source": 73, "target": 50}, {"source": 78, "target": 64}, {"source": 37, "target": 89}, {"source": 26, "target": 59}, {"source": 22, "target": 35}, {"source": 59, "target": 25}, {"source": 79, "target": 87}, {"source": 75, "target": 88}, {"source": 39, "target": 86}, {"source": 2, "target": 19}, {"source": 24, "target": 30}, {"source": 81, "target": 50}, {"source": 92, "target": 9}, {"source": 81, "target": 68}, {"source": 88, "target": 61}, {"source": 9, "target": 86}, {"source": 86, "target": 59}, {"source": 1, "target": 10}, {"source": 49, "target": 56}, {"source": 3, "target": 19}, {"source": 45, "target": 61}, {"source": 47, "target": 26}, {"source": 51, "target": 66}, {"source": 54, "target": 86}, {"source": 39, "target": 32}, {"source": 9, "target": 41}, {"source": 67, "target": 88}, {"source": 53, "target": 83}, {"source": 67, "target": 57}, {"source": 76, "target": 26}, {"source": 24, "target": 53}, {"source": 9, "target": 23}, {"source": 4, "target": 88}, {"source": 35, "target": 78}, {"source": 90, "target": 58}, {"source": 61, "target": 30}, {"source": 44, "target": 50}, {"source": 87, "target": 26}, {"source": 27, "target": 51}, {"source": 3, "target": 13}, {"source": 24, "target": 46}, {"source": 21, "target": 17}, {"source": 49, "target": 73}, {"source": 73, "target": 79}, {"source": 90, "target": 51}, {"source": 60, "target": 24}, {"source": 83, "target": 78}, {"source": 9, "target": 69}, {"source": 59, "target": 66}, {"source": 9, "target": 40}, {"source": 74, "target": 43}, {"source": 61, "target": 86}, {"source": 8, "target": 15}, {"source": 68, "target": 24}, {"source": 13, "target": 2}, {"source": 36, "target": 2}, {"source": 40, "target": 64}, {"source": 26, "target": 39}, {"source": 86, "target": 55}, {"source": 40, "target": 89}, {"source": 62, "target": 30}, {"source": 16, "target": 4}, {"source": 58, "target": 44}, {"source": 31, "target": 48}, {"source": 82, "target": 36}, {"source": 88, "target": 35}, {"source": 9, "target": 73}, {"source": 66, "target": 59}, {"source": 58, "target": 66}, {"source": 61, "target": 51}, {"source": 65, "target": 27}, {"source": 20, "target": 8}, {"source": 67, "target": 27}, {"source": 55, "target": 78}, {"source": 67, "target": 37}, {"source": 30, "target": 61}, {"source": 80, "target": 30}, {"source": 33, "target": 31}, {"source": 81, "target": 45}, {"source": 24, "target": 65}, {"source": 73, "target": 57}, {"source": 59, "target": 67}, {"source": 3, "target": 14}, {"source": 58, "target": 35}, {"source": 91, "target": 41}, {"source": 9, "target": 13}, {"source": 89, "target": 80}, {"source": 33, "target": 47}, {"source": 55, "target": 39}, {"source": 41, "target": 45}, {"source": 23, "target": 71}, {"source": 17, "target": 4}, {"source": 33, "target": 51}, {"source": 79, "target": 57}, {"source": 63, "target": 66}, {"source": 86, "target": 24}, {"source": 46, "target": 86}, {"source": 5, "target": 21}, {"source": 11, "target": 7}, {"source": 81, "target": 48}, {"source": 9, "target": 47}, {"source": 89, "target": 44}, {"source": 65, "target": 35}, {"source": 20, "target": 12}, {"source": 50, "target": 27}, {"source": 51, "target": 9}, {"source": 46, "target": 35}, {"source": 64, "target": 68}, {"source": 47, "target": 9}, {"source": 74, "target": 66}, {"source": 45, "target": 62}, {"source": 80, "target": 50}, {"source": 73, "target": 86}, {"source": 88, "target": 28}, {"source": 47, "target": 69}, {"source": 68, "target": 43}, {"source": 12, "target": 20}, {"source": 35, "target": 26}, {"source": 36, "target": 53}, {"source": 40, "target": 66}, {"source": 10, "target": 13}, {"source": 26, "target": 60}, {"source": 54, "target": 40}, {"source": 53, "target": 45}, {"source": 49, "target": 69}, {"source": 44, "target": 68}, {"source": 2, "target": 8}, {"source": 24, "target": 80}, {"source": 21, "target": 1}, {"source": 57, "target": 61}, {"source": 51, "target": 90}, {"source": 49, "target": 42}, {"source": 53, "target": 2}, {"source": 92, "target": 54}, {"source": 27, "target": 31}, {"source": 27, "target": 33}, {"source": 35, "target": 83}, {"source": 88, "target": 30}, {"source": 17, "target": 88}, {"source": 66, "target": 31}, {"source": 83, "target": 28}, {"source": 51, "target": 87}, {"source": 50, "target": 40}, {"source": 54, "target": 26}, {"source": 19, "target": 2}, {"source": 51, "target": 33}, {"source": 35, "target": 80}, {"source": 15, "target": 13}, {"source": 86, "target": 30}, {"source": 66, "target": 69}, {"source": 79, "target": 67}, {"source": 69, "target": 73}, {"source": 79, "target": 42}, {"source": 68, "target": 37}, {"source": 17, "target": 66}, {"source": 56, "target": 69}, {"source": 69, "target": 74}, {"source": 64, "target": 65}, {"source": 53, "target": 44}, {"source": 55, "target": 26}, {"source": 79, "target": 59}, {"source": 11, "target": 3}, {"source": 35, "target": 61}, {"source": 14, "target": 18}, {"source": 21, "target": 18}, {"source": 7, "target": 21}, {"source": 32, "target": 26}, {"source": 63, "target": 40}, {"source": 78, "target": 46}, {"source": 30, "target": 68}, {"source": 64, "target": 30}, {"source": 92, "target": 48}, {"source": 10, "target": 21}, {"source": 18, "target": 15}, {"source": 17, "target": 68}, {"source": 67, "target": 24}, {"source": 30, "target": 67}, {"source": 1, "target": 16}, {"source": 45, "target": 89}, {"source": 43, "target": 86}, {"source": 11, "target": 19}, {"source": 78, "target": 53}, {"source": 54, "target": 35}, {"source": 49, "target": 58}, {"source": 8, "target": 2}, {"source": 92, "target": 45}, {"source": 82, "target": 28}, {"source": 67, "target": 64}, {"source": 45, "target": 64}, {"source": 14, "target": 15}, {"source": 76, "target": 74}, {"source": 65, "target": 90}, {"source": 27, "target": 58}, {"source": 78, "target": 80}, {"source": 60, "target": 86}, {"source": 51, "target": 65}, {"source": 26, "target": 77}, {"source": 16, "target": 12}, {"source": 88, "target": 24}, {"source": 59, "target": 35}, {"source": 65, "target": 15}, {"source": 19, "target": 3}, {"source": 51, "target": 42}, {"source": 78, "target": 81}, {"source": 89, "target": 75}, {"source": 44, "target": 47}, {"source": 16, "target": 3}, {"source": 43, "target": 58}, {"source": 70, "target": 2}, {"source": 74, "target": 69}, {"source": 70, "target": 92}, {"source": 27, "target": 69}, {"source": 41, "target": 65}, {"source": 43, "target": 74}, {"source": 92, "target": 46}, {"source": 50, "target": 44}, {"source": 36, "target": 60}, {"source": 58, "target": 36}, {"source": 9, "target": 6}, {"source": 17, "target": 71}, {"source": 26, "target": 53}, {"source": 50, "target": 48}, {"source": 26, "target": 44}, {"source": 63, "target": 78}, {"source": 4, "target": 10}, {"source": 54, "target": 39}, {"source": 2, "target": 9}, {"source": 80, "target": 24}, {"source": 86, "target": 64}, {"source": 55, "target": 68}, {"source": 2, "target": 7}, {"source": 12, "target": 19}, {"source": 4, "target": 20}, {"source": 52, "target": 26}, {"source": 15, "target": 8}, {"source": 26, "target": 80}, {"source": 88, "target": 40}, {"source": 68, "target": 81}, {"source": 82, "target": 45}, {"source": 13, "target": 20}, {"source": 3, "target": 12}, {"source": 92, "target": 30}, {"source": 47, "target": 57}, {"source": 20, "target": 17}, {"source": 27, "target": 79}, {"source": 81, "target": 55}, {"source": 40, "target": 17}, {"source": 88, "target": 4}, {"source": 90, "target": 76}, {"source": 9, "target": 51}, {"source": 49, "target": 27}, {"source": 36, "target": 35}, {"source": 90, "target": 77}, {"source": 88, "target": 67}, {"source": 1, "target": 8}, {"source": 81, "target": 46}, {"source": 25, "target": 76}, {"source": 42, "target": 39}, {"source": 30, "target": 87}, {"source": 60, "target": 67}, {"source": 35, "target": 51}, {"source": 54, "target": 75}, {"source": 27, "target": 50}, {"source": 7, "target": 1}, {"source": 85, "target": 17}, {"source": 25, "target": 69}, {"source": 39, "target": 70}, {"source": 77, "target": 27}, {"source": 23, "target": 84}, {"source": 63, "target": 27}, {"source": 20, "target": 10}, {"source": 88, "target": 78}, {"source": 30, "target": 88}, {"source": 26, "target": 2}, {"source": 20, "target": 3}, {"source": 45, "target": 54}, {"source": 61, "target": 56}, {"source": 78, "target": 60}, {"source": 38, "target": 71}, {"source": 37, "target": 41}, {"source": 66, "target": 85}, {"source": 46, "target": 80}, {"source": 4, "target": 19}, {"source": 53, "target": 40}, {"source": 86, "target": 78}, {"source": 76, "target": 28}, {"source": 46, "target": 81}, {"source": 58, "target": 39}, {"source": 54, "target": 37}, {"source": 64, "target": 63}, {"source": 69, "target": 43}, {"source": 68, "target": 51}, {"source": 86, "target": 69}, {"source": 21, "target": 8}, {"source": 43, "target": 87}, {"source": 33, "target": 79}, {"source": 31, "target": 27}, {"source": 28, "target": 78}, {"source": 87, "target": 73}, {"source": 36, "target": 80}, {"source": 40, "target": 41}, {"source": 33, "target": 43}, {"source": 26, "target": 32}, {"source": 48, "target": 81}, {"source": 46, "target": 55}, {"source": 89, "target": 35}, {"source": 46, "target": 2}, {"source": 87, "target": 30}, {"source": 40, "target": 86}, {"source": 73, "target": 25}, {"source": 2, "target": 88}, {"source": 43, "target": 27}, {"source": 76, "target": 83}, {"source": 27, "target": 77}, {"source": 47, "target": 86}, {"source": 27, "target": 76}, {"source": 25, "target": 61}, {"source": 56, "target": 65}, {"source": 75, "target": 81}, {"source": 68, "target": 30}, {"source": 56, "target": 78}, {"source": 51, "target": 77}, {"source": 30, "target": 45}, {"source": 51, "target": 76}, {"source": 54, "target": 44}, {"source": 20, "target": 13}, {"source": 1, "target": 20}, {"source": 28, "target": 83}, {"source": 1, "target": 9}, {"source": 1, "target": 14}, {"source": 39, "target": 26}, {"source": 11, "target": 20}, {"source": 77, "target": 51}, {"source": 24, "target": 59}, {"source": 66, "target": 34}, {"source": 58, "target": 51}, {"source": 61, "target": 40}, {"source": 54, "target": 83}, {"source": 14, "target": 3}, {"source": 49, "target": 83}, {"source": 87, "target": 9}, {"source": 92, "target": 50}, {"source": 3, "target": 8}, {"source": 62, "target": 61}, {"source": 45, "target": 24}, {"source": 3, "target": 10}, {"source": 80, "target": 55}, {"source": 80, "target": 41}, {"source": 70, "target": 24}, {"source": 40, "target": 92}, {"source": 75, "target": 9}, {"source": 75, "target": 64}, {"source": 73, "target": 42}, {"source": 79, "target": 77}, {"source": 80, "target": 83}, {"source": 68, "target": 62}, {"source": 80, "target": 86}, {"source": 46, "target": 50}, {"source": 1, "target": 11}, {"source": 69, "target": 50}, {"source": 2, "target": 16}, {"source": 26, "target": 33}, {"source": 28, "target": 26}, {"source": 14, "target": 39}, {"source": 41, "target": 63}, {"source": 58, "target": 37}, {"source": 17, "target": 87}, {"source": 75, "target": 35}, {"source": 86, "target": 37}, {"source": 38, "target": 64}, {"source": 78, "target": 68}, {"source": 54, "target": 78}, {"source": 71, "target": 87}, {"source": 75, "target": 89}, {"source": 12, "target": 16}, {"source": 51, "target": 44}, {"source": 35, "target": 38}, {"source": 48, "target": 71}, {"source": 35, "target": 82}, {"source": 65, "target": 40}, {"source": 89, "target": 65}, {"source": 14, "target": 8}, {"source": 26, "target": 55}, {"source": 35, "target": 58}, {"source": 30, "target": 55}, {"source": 60, "target": 39}, {"source": 88, "target": 46}, {"source": 11, "target": 1}, {"source": 61, "target": 78}, {"source": 64, "target": 40}, {"source": 50, "target": 73}, {"source": 35, "target": 60}, {"source": 89, "target": 47}, {"source": 65, "target": 73}, {"source": 59, "target": 47}, {"source": 30, "target": 24}, {"source": 26, "target": 92}, {"source": 11, "target": 10}, {"source": 32, "target": 73}, {"source": 92, "target": 81}, {"source": 9, "target": 54}, {"source": 4, "target": 8}, {"source": 26, "target": 27}, {"source": 24, "target": 64}, {"source": 66, "target": 51}, {"source": 87, "target": 65}, {"source": 43, "target": 33}, {"source": 25, "target": 27}, {"source": 61, "target": 76}, {"source": 81, "target": 75}, {"source": 51, "target": 24}, {"source": 83, "target": 65}, {"source": 66, "target": 74}, {"source": 88, "target": 39}, {"source": 73, "target": 40}, {"source": 89, "target": 46}, {"source": 58, "target": 33}, {"source": 2, "target": 80}, {"source": 78, "target": 50}, {"source": 50, "target": 75}, {"source": 64, "target": 50}, {"source": 42, "target": 79}, {"source": 39, "target": 78}, {"source": 17, "target": 13}, {"source": 83, "target": 73}, {"source": 39, "target": 54}, {"source": 61, "target": 73}, {"source": 88, "target": 2}, {"source": 50, "target": 41}, {"source": 75, "target": 82}, {"source": 74, "target": 86}, {"source": 25, "target": 43}, {"source": 81, "target": 83}, {"source": 81, "target": 40}, {"source": 89, "target": 73}, {"source": 43, "target": 77}, {"source": 30, "target": 80}, {"source": 65, "target": 69}, {"source": 59, "target": 24}, {"source": 64, "target": 39}, {"source": 68, "target": 61}, {"source": 50, "target": 86}, {"source": 44, "target": 57}, {"source": 25, "target": 86}, {"source": 32, "target": 64}, {"source": 76, "target": 39}, {"source": 41, "target": 91}, {"source": 88, "target": 75}, {"source": 68, "target": 54}, {"source": 36, "target": 78}, {"source": 74, "target": 33}, {"source": 24, "target": 70}, {"source": 34, "target": 63}, {"source": 71, "target": 69}, {"source": 24, "target": 58}, {"source": 66, "target": 41}, {"source": 82, "target": 35}, {"source": 86, "target": 43}, {"source": 45, "target": 55}, {"source": 89, "target": 9}, {"source": 78, "target": 88}, {"source": 17, "target": 69}, {"source": 80, "target": 35}, {"source": 12, "target": 3}, {"source": 21, "target": 10}, {"source": 77, "target": 58}, {"source": 58, "target": 86}, {"source": 32, "target": 78}, {"source": 88, "target": 55}, {"source": 46, "target": 9}, {"source": 23, "target": 92}, {"source": 17, "target": 3}, {"source": 88, "target": 37}, {"source": 41, "target": 50}, {"source": 71, "target": 38}, {"source": 81, "target": 86}, {"source": 35, "target": 76}, {"source": 3, "target": 11}, {"source": 65, "target": 83}, {"source": 35, "target": 53}, {"source": 24, "target": 86}, {"source": 79, "target": 69}, {"source": 40, "target": 39}, {"source": 44, "target": 80}, {"source": 26, "target": 57}, {"source": 83, "target": 39}, {"source": 51, "target": 74}, {"source": 57, "target": 25}, {"source": 26, "target": 88}, {"source": 17, "target": 75}, {"source": 43, "target": 51}, {"source": 62, "target": 80}, {"source": 61, "target": 35}, {"source": 2, "target": 14}, {"source": 19, "target": 14}, {"source": 51, "target": 71}, {"source": 42, "target": 49}, {"source": 40, "target": 50}, {"source": 12, "target": 14}, {"source": 16, "target": 14}, {"source": 72, "target": 33}, {"source": 71, "target": 23}, {"source": 68, "target": 44}, {"source": 7, "target": 10}, {"source": 69, "target": 51}, {"source": 36, "target": 64}, {"source": 39, "target": 64}, {"source": 77, "target": 79}, {"source": 35, "target": 22}, {"source": 17, "target": 23}, {"source": 24, "target": 47}, {"source": 47, "target": 43}, {"source": 73, "target": 89}, {"source": 51, "target": 43}, {"source": 54, "target": 71}, {"source": 9, "target": 63}, {"source": 28, "target": 39}, {"source": 76, "target": 35}, {"source": 61, "target": 25}, {"source": 41, "target": 17}, {"source": 24, "target": 67}, {"source": 55, "target": 45}, {"source": 73, "target": 69}, {"source": 35, "target": 68}, {"source": 66, "target": 36}, {"source": 58, "target": 17}, {"source": 86, "target": 27}, {"source": 39, "target": 36}, {"source": 49, "target": 76}, {"source": 14, "target": 7}, {"source": 14, "target": 20}, {"source": 68, "target": 80}, {"source": 22, "target": 55}, {"source": 66, "target": 45}, {"source": 56, "target": 33}, {"source": 46, "target": 39}, {"source": 82, "target": 24}, {"source": 37, "target": 54}, {"source": 61, "target": 59}, {"source": 24, "target": 75}, {"source": 78, "target": 61}, {"source": 76, "target": 65}, {"source": 37, "target": 46}, {"source": 18, "target": 19}, {"source": 4, "target": 39}, {"source": 13, "target": 6}, {"source": 49, "target": 65}, {"source": 86, "target": 22}, {"source": 74, "target": 73}, {"source": 51, "target": 56}, {"source": 28, "target": 56}, {"source": 53, "target": 78}, {"source": 39, "target": 42}, {"source": 83, "target": 53}, {"source": 10, "target": 20}, {"source": 31, "target": 66}, {"source": 36, "target": 66}, {"source": 32, "target": 75}, {"source": 17, "target": 45}, {"source": 47, "target": 42}, {"source": 41, "target": 35}, {"source": 26, "target": 69}, {"source": 22, "target": 24}, {"source": 61, "target": 90}, {"source": 54, "target": 55}, {"source": 35, "target": 40}, {"source": 2, "target": 53}, {"source": 27, "target": 26}, {"source": 4, "target": 3}, {"source": 74, "target": 26}, {"source": 45, "target": 53}, {"source": 27, "target": 57}, {"source": 26, "target": 28}, {"source": 72, "target": 74}, {"source": 35, "target": 4}, {"source": 68, "target": 17}, {"source": 55, "target": 61}, {"source": 47, "target": 41}, {"source": 65, "target": 43}, {"source": 68, "target": 88}, {"source": 25, "target": 47}, {"source": 17, "target": 20}, {"source": 51, "target": 59}, {"source": 67, "target": 60}, {"source": 87, "target": 58}, {"source": 89, "target": 37}, {"source": 36, "target": 39}, {"source": 43, "target": 25}, {"source": 69, "target": 48}, {"source": 9, "target": 85}, {"source": 9, "target": 37}, {"source": 75, "target": 80}, {"source": 43, "target": 65}, {"source": 83, "target": 88}, {"source": 35, "target": 50}, {"source": 28, "target": 9}, {"source": 65, "target": 39}, {"source": 50, "target": 78}, {"source": 92, "target": 70}, {"source": 57, "target": 32}, {"source": 41, "target": 24}, {"source": 22, "target": 2}, {"source": 24, "target": 89}, {"source": 1, "target": 12}, {"source": 74, "target": 87}, {"source": 73, "target": 45}, {"source": 1, "target": 13}, {"source": 34, "target": 66}, {"source": 65, "target": 58}, {"source": 65, "target": 77}, {"source": 78, "target": 73}, {"source": 59, "target": 26}, {"source": 24, "target": 66}, {"source": 64, "target": 86}, {"source": 58, "target": 77}, {"source": 27, "target": 25}, {"source": 51, "target": 47}, {"source": 48, "target": 66}, {"source": 20, "target": 19}, {"source": 9, "target": 17}, {"source": 20, "target": 4}, {"source": 58, "target": 78}, {"source": 33, "target": 49}, {"source": 55, "target": 82}, {"source": 28, "target": 25}, {"source": 89, "target": 63}, {"source": 73, "target": 46}, {"source": 15, "target": 17}, {"source": 19, "target": 16}, {"source": 51, "target": 35}, {"source": 27, "target": 47}, {"source": 69, "target": 47}, {"source": 54, "target": 38}, {"source": 49, "target": 25}, {"source": 26, "target": 74}, {"source": 87, "target": 27}, {"source": 25, "target": 28}, {"source": 62, "target": 45}, {"source": 65, "target": 26}, {"source": 26, "target": 58}, {"source": 64, "target": 35}, {"source": 9, "target": 1}, {"source": 35, "target": 65}, {"source": 26, "target": 49}, {"source": 42, "target": 43}, {"source": 46, "target": 40}, {"source": 86, "target": 46}, {"source": 58, "target": 62}, {"source": 34, "target": 41}, {"source": 37, "target": 9}, {"source": 21, "target": 9}, {"source": 50, "target": 69}, {"source": 78, "target": 41}, {"source": 85, "target": 9}, {"source": 45, "target": 78}, {"source": 41, "target": 89}, {"source": 61, "target": 68}, {"source": 88, "target": 80}, {"source": 54, "target": 46}, {"source": 42, "target": 90}, {"source": 16, "target": 8}, {"source": 26, "target": 86}, {"source": 29, "target": 24}, {"source": 55, "target": 80}, {"source": 18, "target": 7}, {"source": 77, "target": 86}, {"source": 32, "target": 55}, {"source": 83, "target": 86}, {"source": 35, "target": 75}, {"source": 78, "target": 86}, {"source": 53, "target": 86}, {"source": 14, "target": 13}, {"source": 24, "target": 32}, {"source": 78, "target": 22}, {"source": 86, "target": 80}, {"source": 24, "target": 83}, {"source": 61, "target": 58}, {"source": 39, "target": 4}, {"source": 51, "target": 69}, {"source": 88, "target": 68}, {"source": 39, "target": 45}, {"source": 92, "target": 41}, {"source": 42, "target": 28}, {"source": 46, "target": 32}, {"source": 25, "target": 33}, {"source": 83, "target": 54}, {"source": 80, "target": 62}, {"source": 35, "target": 63}, {"source": 55, "target": 81}, {"source": 92, "target": 86}, {"source": 75, "target": 68}, {"source": 53, "target": 58}, {"source": 39, "target": 75}, {"source": 86, "target": 73}, {"source": 17, "target": 80}, {"source": 47, "target": 79}, {"source": 23, "target": 9}, {"source": 40, "target": 46}, {"source": 80, "target": 63}, {"source": 36, "target": 51}, {"source": 23, "target": 41}, {"source": 23, "target": 17}, {"source": 83, "target": 81}, {"source": 37, "target": 45}, {"source": 69, "target": 71}, {"source": 61, "target": 43}, {"source": 73, "target": 83}, {"source": 7, "target": 5}, {"source": 86, "target": 47}, {"source": 58, "target": 92}, {"source": 64, "target": 75}, {"source": 32, "target": 86}, {"source": 51, "target": 83}, {"source": 26, "target": 70}, {"source": 64, "target": 92}, {"source": 59, "target": 53}, {"source": 60, "target": 54}, {"source": 85, "target": 31}, {"source": 6, "target": 13}, {"source": 50, "target": 9}, {"source": 89, "target": 51}, {"source": 26, "target": 87}, {"source": 27, "target": 87}, {"source": 54, "target": 60}, {"source": 60, "target": 26}, {"source": 45, "target": 49}, {"source": 80, "target": 2}, {"source": 9, "target": 46}, {"source": 30, "target": 39}, {"source": 43, "target": 56}, {"source": 40, "target": 54}, {"source": 26, "target": 67}, {"source": 68, "target": 48}, {"source": 47, "target": 24}, {"source": 90, "target": 43}, {"source": 78, "target": 26}, {"source": 66, "target": 40}, {"source": 65, "target": 24}, {"source": 17, "target": 63}, {"source": 91, "target": 33}, {"source": 30, "target": 75}, {"source": 63, "target": 80}, {"source": 90, "target": 79}, {"source": 80, "target": 40}, {"source": 55, "target": 17}, {"source": 64, "target": 67}, {"source": 40, "target": 30}, {"source": 41, "target": 62}, {"source": 9, "target": 87}, {"source": 37, "target": 26}, {"source": 13, "target": 18}, {"source": 53, "target": 88}, {"source": 79, "target": 43}, {"source": 12, "target": 7}, {"source": 64, "target": 24}, {"source": 55, "target": 59}, {"source": 74, "target": 76}, {"source": 60, "target": 80}, {"source": 58, "target": 90}, {"source": 24, "target": 41}, {"source": 39, "target": 60}, {"source": 64, "target": 88}, {"source": 65, "target": 47}, {"source": 53, "target": 37}, {"source": 58, "target": 53}, {"source": 75, "target": 78}, {"source": 43, "target": 69}, {"source": 35, "target": 34}, {"source": 9, "target": 4}, {"source": 38, "target": 68}, {"source": 71, "target": 48}, {"source": 51, "target": 58}, {"source": 16, "target": 2}, {"source": 45, "target": 66}, {"source": 69, "target": 27}, {"source": 33, "target": 27}, {"source": 56, "target": 91}, {"source": 62, "target": 53}, {"source": 46, "target": 26}, {"source": 17, "target": 18}, {"source": 51, "target": 34}, {"source": 37, "target": 80}, {"source": 40, "target": 63}, {"source": 76, "target": 59}, {"source": 57, "target": 79}, {"source": 63, "target": 51}, {"source": 69, "target": 61}, {"source": 71, "target": 68}, {"source": 88, "target": 9}, {"source": 21, "target": 19}, {"source": 65, "target": 44}, {"source": 24, "target": 68}, {"source": 45, "target": 39}, {"source": 14, "target": 1}, {"source": 44, "target": 53}, {"source": 57, "target": 27}, {"source": 73, "target": 43}, {"source": 61, "target": 26}, {"source": 32, "target": 44}, {"source": 88, "target": 53}, {"source": 24, "target": 54}, {"source": 81, "target": 54}, {"source": 35, "target": 70}, {"source": 81, "target": 78}, {"source": 18, "target": 17}, {"source": 86, "target": 33}, {"source": 92, "target": 64}, {"source": 80, "target": 88}, {"source": 71, "target": 17}, {"source": 33, "target": 26}, {"source": 65, "target": 89}, {"source": 68, "target": 40}, {"source": 45, "target": 82}, {"source": 7, "target": 9}, {"source": 82, "target": 39}, {"source": 49, "target": 33}, {"source": 42, "target": 44}, {"source": 66, "target": 63}, {"source": 27, "target": 42}, {"source": 28, "target": 63}, {"source": 51, "target": 79}, {"source": 37, "target": 82}, {"source": 63, "target": 39}, {"source": 50, "target": 37}, {"source": 22, "target": 86}, {"source": 82, "target": 75}, {"source": 49, "target": 26}, {"source": 5, "target": 7}, {"source": 53, "target": 59}, {"source": 33, "target": 57}, {"source": 17, "target": 85}, {"source": 39, "target": 80}, {"source": 79, "target": 33}, {"source": 5, "target": 3}, {"source": 20, "target": 11}, {"source": 91, "target": 56}, {"source": 9, "target": 20}, {"source": 68, "target": 26}, {"source": 71, "target": 50}, {"source": 28, "target": 88}, {"source": 28, "target": 65}, {"source": 43, "target": 26}, {"source": 42, "target": 73}, {"source": 60, "target": 68}, {"source": 68, "target": 46}, {"source": 13, "target": 17}, {"source": 14, "target": 2}, {"source": 63, "target": 61}, {"source": 65, "target": 87}, {"source": 2, "target": 4}, {"source": 58, "target": 24}, {"source": 51, "target": 61}, {"source": 28, "target": 37}, {"source": 58, "target": 26}, {"source": 13, "target": 15}, {"source": 28, "target": 60}, {"source": 19, "target": 12}, {"source": 78, "target": 39}, {"source": 56, "target": 76}, {"source": 2, "target": 36}, {"source": 9, "target": 7}, {"source": 38, "target": 50}, {"source": 40, "target": 55}, {"source": 58, "target": 73}, {"source": 81, "target": 92}, {"source": 74, "target": 25}, {"source": 68, "target": 55}, {"source": 12, "target": 8}, {"source": 24, "target": 88}, {"source": 41, "target": 47}, {"source": 68, "target": 38}, {"source": 55, "target": 37}, {"source": 69, "target": 44}, {"source": 49, "target": 86}, {"source": 57, "target": 73}, {"source": 68, "target": 45}, {"source": 44, "target": 86}, {"source": 40, "target": 88}, {"source": 77, "target": 90}, {"source": 24, "target": 40}, {"source": 81, "target": 26}, {"source": 89, "target": 26}, {"source": 76, "target": 63}, {"source": 83, "target": 76}, {"source": 44, "target": 41}, {"source": 66, "target": 71}, {"source": 8, "target": 19}, {"source": 15, "target": 14}, {"source": 18, "target": 14}, {"source": 26, "target": 68}, {"source": 48, "target": 72}, {"source": 24, "target": 61}, {"source": 86, "target": 17}, {"source": 87, "target": 76}, {"source": 17, "target": 6}, {"source": 33, "target": 86}, {"source": 26, "target": 47}, {"source": 7, "target": 11}, {"source": 31, "target": 33}, {"source": 74, "target": 59}, {"source": 7, "target": 14}, {"source": 8, "target": 14}, {"source": 20, "target": 14}, {"source": 7, "target": 17}, {"source": 35, "target": 46}, {"source": 58, "target": 57}, {"source": 55, "target": 35}, {"source": 26, "target": 43}, {"source": 41, "target": 9}, {"source": 17, "target": 15}, {"source": 80, "target": 46}, {"source": 64, "target": 54}, {"source": 78, "target": 28}, {"source": 41, "target": 59}, {"source": 32, "target": 53}, {"source": 46, "target": 88}, {"source": 63, "target": 28}, {"source": 74, "target": 56}, {"source": 42, "target": 74}, {"source": 69, "target": 65}, {"source": 64, "target": 38}, {"source": 30, "target": 86}, {"source": 89, "target": 40}, {"source": 66, "target": 24}, {"source": 43, "target": 68}, {"source": 49, "target": 59}, {"source": 39, "target": 68}, {"source": 68, "target": 50}, {"source": 42, "target": 51}, {"source": 26, "target": 51}, {"source": 37, "target": 40}, {"source": 53, "target": 66}, {"source": 4, "target": 28}, {"source": 47, "target": 25}, {"source": 54, "target": 53}, {"source": 74, "target": 61}, {"source": 45, "target": 37}, {"source": 21, "target": 16}, {"source": 92, "target": 53}, {"source": 82, "target": 78}, {"source": 78, "target": 35}, {"source": 87, "target": 61}, {"source": 91, "target": 74}, {"source": 71, "target": 34}, {"source": 40, "target": 68}, {"source": 64, "target": 46}, {"source": 75, "target": 17}, {"source": 4, "target": 2}, {"source": 24, "target": 78}, {"source": 55, "target": 54}, {"source": 71, "target": 41}, {"source": 39, "target": 57}, {"source": 59, "target": 49}, {"source": 79, "target": 73}, {"source": 36, "target": 88}, {"source": 25, "target": 51}, {"source": 81, "target": 28}, {"source": 18, "target": 21}, {"source": 83, "target": 68}, {"source": 53, "target": 32}, {"source": 40, "target": 80}, {"source": 39, "target": 63}, {"source": 47, "target": 74}, {"source": 54, "target": 51}, {"source": 1, "target": 21}, {"source": 80, "target": 22}, {"source": 17, "target": 86}, {"source": 81, "target": 80}, {"source": 51, "target": 54}, {"source": 51, "target": 67}, {"source": 17, "target": 55}, {"source": 86, "target": 77}, {"source": 58, "target": 55}, {"source": 78, "target": 32}, {"source": 7, "target": 20}, {"source": 53, "target": 92}, {"source": 7, "target": 4}, {"source": 17, "target": 34}, {"source": 70, "target": 86}, {"source": 51, "target": 86}, {"source": 45, "target": 86}, {"source": 80, "target": 78}, {"source": 9, "target": 89}, {"source": 35, "target": 66}, {"source": 13, "target": 10}, {"source": 56, "target": 61}, {"source": 73, "target": 66}, {"source": 27, "target": 86}, {"source": 45, "target": 41}, {"source": 87, "target": 69}, {"source": 31, "target": 69}, {"source": 22, "target": 39}, {"source": 41, "target": 66}, {"source": 60, "target": 82}, {"source": 46, "target": 54}, {"source": 92, "target": 23}, {"source": 39, "target": 55}, {"source": 10, "target": 7}, {"source": 63, "target": 41}, {"source": 26, "target": 30}, {"source": 53, "target": 47}, {"source": 58, "target": 30}, {"source": 76, "target": 43}, {"source": 64, "target": 44}, {"source": 87, "target": 79}, {"source": 67, "target": 59}, {"source": 41, "target": 71}, {"source": 63, "target": 76}, {"source": 78, "target": 9}, {"source": 75, "target": 54}, {"source": 62, "target": 40}, {"source": 87, "target": 71}, {"source": 26, "target": 54}, {"source": 46, "target": 17}, {"source": 50, "target": 92}, {"source": 78, "target": 63}, {"source": 25, "target": 65}, {"source": 78, "target": 40}, {"source": 13, "target": 1}, {"source": 51, "target": 73}, {"source": 26, "target": 79}, {"source": 41, "target": 67}, {"source": 30, "target": 78}, {"source": 41, "target": 23}, {"source": 12, "target": 1}, {"source": 40, "target": 24}, {"source": 75, "target": 39}, {"source": 73, "target": 33}, {"source": 45, "target": 46}, {"source": 40, "target": 87}, {"source": 79, "target": 74}, {"source": 42, "target": 86}, {"source": 18, "target": 20}, {"source": 30, "target": 64}, {"source": 17, "target": 54}, {"source": 61, "target": 88}, {"source": 44, "target": 73}, {"source": 4, "target": 9}, {"source": 71, "target": 64}, {"source": 86, "target": 49}, {"source": 8, "target": 16}, {"source": 20, "target": 16}, {"source": 79, "target": 51}, {"source": 39, "target": 53}, {"source": 62, "target": 41}, {"source": 71, "target": 54}, {"source": 5, "target": 6}, {"source": 13, "target": 8}, {"source": 39, "target": 83}, {"source": 83, "target": 51}, {"source": 49, "target": 87}, {"source": 86, "target": 82}, {"source": 47, "target": 49}, {"source": 63, "target": 35}, {"source": 57, "target": 42}, {"source": 71, "target": 84}, {"source": 42, "target": 58}, {"source": 82, "target": 26}, {"source": 73, "target": 78}, {"source": 28, "target": 82}, {"source": 78, "target": 37}, {"source": 44, "target": 25}, {"source": 63, "target": 89}, {"source": 31, "target": 77}, {"source": 41, "target": 87}, {"source": 17, "target": 84}, {"source": 27, "target": 65}, {"source": 79, "target": 25}, {"source": 83, "target": 55}, {"source": 69, "target": 90}, {"source": 9, "target": 71}, {"source": 82, "target": 32}, {"source": 64, "target": 36}, {"source": 40, "target": 78}, {"source": 45, "target": 40}, {"source": 3, "target": 21}, {"source": 73, "target": 27}, {"source": 76, "target": 49}, {"source": 79, "target": 47}, {"source": 48, "target": 68}, {"source": 42, "target": 78}, {"source": 39, "target": 40}, {"source": 86, "target": 51}, {"source": 54, "target": 45}, {"source": 21, "target": 14}, {"source": 24, "target": 43}, {"source": 13, "target": 5}, {"source": 85, "target": 37}, {"source": 86, "target": 58}, {"source": 37, "target": 28}, {"source": 65, "target": 33}, {"source": 74, "target": 47}, {"source": 86, "target": 74}, {"source": 28, "target": 86}, {"source": 44, "target": 43}, {"source": 57, "target": 47}, {"source": 83, "target": 60}, {"source": 35, "target": 54}, {"source": 1, "target": 7}, {"source": 7, "target": 19}, {"source": 58, "target": 42}, {"source": 58, "target": 67}, {"source": 62, "target": 68}, {"source": 86, "target": 39}, {"source": 42, "target": 63}, {"source": 78, "target": 45}, {"source": 14, "target": 4}, {"source": 62, "target": 63}, {"source": 33, "target": 72}, {"source": 49, "target": 61}, {"source": 39, "target": 87}, {"source": 56, "target": 74}, {"source": 28, "target": 35}, {"source": 39, "target": 61}, {"source": 21, "target": 13}, {"source": 56, "target": 51}, {"source": 73, "target": 51}, {"source": 4, "target": 11}, {"source": 37, "target": 58}, {"source": 58, "target": 54}, {"source": 25, "target": 26}, {"source": 8, "target": 12}, {"source": 86, "target": 40}, {"source": 88, "target": 26}, {"source": 25, "target": 44}, {"source": 30, "target": 17}, {"source": 48, "target": 50}, {"source": 86, "target": 53}, {"source": 10, "target": 14}, {"source": 80, "target": 39}, {"source": 67, "target": 41}, {"source": 61, "target": 62}, {"source": 30, "target": 35}, {"source": 34, "target": 51}, {"source": 7, "target": 13}, {"source": 29, "target": 63}, {"source": 81, "target": 35}, {"source": 40, "target": 35}, {"source": 67, "target": 86}, {"source": 53, "target": 46}, {"source": 20, "target": 7}, {"source": 14, "target": 11}, {"source": 53, "target": 62}, {"source": 80, "target": 58}, {"source": 7, "target": 12}, {"source": 82, "target": 37}, {"source": 68, "target": 60}, {"source": 45, "target": 30}, {"source": 24, "target": 55}, {"source": 86, "target": 50}, {"source": 57, "target": 49}, {"source": 60, "target": 28}, {"source": 68, "target": 86}, {"source": 41, "target": 46}, {"source": 37, "target": 53}, {"source": 79, "target": 58}, {"source": 59, "target": 43}, {"source": 35, "target": 28}, {"source": 12, "target": 13}, {"source": 80, "target": 81}, {"source": 85, "target": 41}, {"source": 46, "target": 45}, {"source": 7, "target": 2}, {"source": 35, "target": 64}, {"source": 41, "target": 43}, {"source": 42, "target": 25}, {"source": 35, "target": 86}, {"source": 9, "target": 78}, {"source": 40, "target": 9}, {"source": 28, "target": 76}, {"source": 50, "target": 71}, {"source": 13, "target": 21}, {"source": 47, "target": 27}, {"source": 35, "target": 41}, {"source": 47, "target": 89}, {"source": 66, "target": 53}, {"source": 69, "target": 42}, {"source": 3, "target": 1}, {"source": 87, "target": 51}, {"source": 2, "target": 21}, {"source": 32, "target": 57}, {"source": 88, "target": 86}, {"source": 49, "target": 57}, {"source": 10, "target": 1}, {"source": 18, "target": 13}, {"source": 53, "target": 54}, {"source": 39, "target": 82}, {"source": 26, "target": 17}, {"source": 41, "target": 92}, {"source": 55, "target": 53}, {"source": 41, "target": 44}, {"source": 42, "target": 33}, {"source": 26, "target": 35}, {"source": 26, "target": 36}, {"source": 86, "target": 35}, {"source": 75, "target": 45}, {"source": 40, "target": 62}, {"source": 88, "target": 83}, {"source": 83, "target": 26}, {"source": 86, "target": 68}, {"source": 90, "target": 69}, {"source": 17, "target": 5}, {"source": 26, "target": 45}, {"source": 75, "target": 50}, {"source": 70, "target": 82}, {"source": 26, "target": 75}, {"source": 92, "target": 32}, {"source": 51, "target": 68}, {"source": 90, "target": 42}, {"source": 59, "target": 79}, {"source": 9, "target": 88}, {"source": 78, "target": 17}, {"source": 24, "target": 29}, {"source": 55, "target": 58}, {"source": 13, "target": 3}, {"source": 19, "target": 10}, {"source": 44, "target": 42}, {"source": 17, "target": 7}, {"source": 88, "target": 54}, {"source": 74, "target": 91}, {"source": 34, "target": 17}, {"source": 73, "target": 32}, {"source": 32, "target": 46}, {"source": 43, "target": 76}, {"source": 67, "target": 26}, {"source": 25, "target": 79}, {"source": 17, "target": 41}, {"source": 45, "target": 75}, {"source": 19, "target": 11}, {"source": 86, "target": 26}, {"source": 25, "target": 74}, {"source": 7, "target": 16}, {"source": 50, "target": 54}, {"source": 55, "target": 83}, {"source": 66, "target": 87}, {"source": 43, "target": 59}, {"source": 47, "target": 51}, {"source": 35, "target": 36}, {"source": 50, "target": 80}, {"source": 61, "target": 87}, {"source": 45, "target": 26}, {"source": 61, "target": 24}, {"source": 50, "target": 81}, {"source": 5, "target": 17}, {"source": 4, "target": 17}, {"source": 37, "target": 68}, {"source": 64, "target": 32}, {"source": 24, "target": 22}, {"source": 32, "target": 67}, {"source": 30, "target": 40}, {"source": 79, "target": 26}, {"source": 10, "target": 16}, {"source": 41, "target": 80}, {"source": 13, "target": 14}, {"source": 4, "target": 21}, {"source": 63, "target": 9}, {"source": 77, "target": 67}, {"source": 21, "target": 20}, {"source": 69, "target": 9}, {"source": 54, "target": 50}, {"source": 17, "target": 78}, {"source": 26, "target": 81}, {"source": 4, "target": 13}, {"source": 26, "target": 46}, {"source": 86, "target": 44}, {"source": 46, "target": 68}, {"source": 20, "target": 21}, {"source": 11, "target": 14}, {"source": 73, "target": 9}, {"source": 14, "target": 10}, {"source": 9, "target": 42}, {"source": 57, "target": 26}, {"source": 16, "target": 21}, {"source": 37, "target": 67}, {"source": 45, "target": 92}, {"source": 32, "target": 82}, {"source": 8, "target": 21}, {"source": 30, "target": 37}, {"source": 24, "target": 34}, {"source": 8, "target": 4}, {"source": 8, "target": 13}, {"source": 43, "target": 90}, {"source": 84, "target": 23}, {"source": 20, "target": 1}, {"source": 40, "target": 61}, {"source": 35, "target": 59}, {"source": 74, "target": 79}, {"source": 88, "target": 64}, {"source": 45, "target": 81}, {"source": 80, "target": 70}, {"source": 87, "target": 25}, {"source": 66, "target": 73}, {"source": 80, "target": 44}, {"source": 35, "target": 88}, {"source": 73, "target": 44}, {"source": 45, "target": 80}, {"source": 39, "target": 88}, {"source": 88, "target": 36}, {"source": 87, "target": 17}, {"source": 6, "target": 17}, {"source": 50, "target": 64}, {"source": 9, "target": 3}, {"source": 51, "target": 89}, {"source": 35, "target": 81}, {"source": 25, "target": 57}, {"source": 51, "target": 63}, {"source": 33, "target": 58}, {"source": 83, "target": 82}, {"source": 44, "target": 64}, {"source": 13, "target": 4}, {"source": 78, "target": 75}, {"source": 33, "target": 91}, {"source": 35, "target": 55}, {"source": 47, "target": 53}, {"source": 39, "target": 28}, {"source": 77, "target": 26}, {"source": 61, "target": 42}, {"source": 1, "target": 19}, {"source": 37, "target": 85}, {"source": 27, "target": 63}, {"source": 86, "target": 60}, {"source": 7, "target": 18}, {"source": 60, "target": 40}, {"source": 2, "target": 61}, {"source": 30, "target": 82}, {"source": 67, "target": 58}, {"source": 10, "target": 19}, {"source": 5, "target": 9}, {"source": 69, "target": 17}, {"source": 2, "target": 11}, {"source": 60, "target": 78}, {"source": 57, "target": 67}, {"source": 68, "target": 39}, {"source": 33, "target": 42}, {"source": 55, "target": 30}, {"source": 54, "target": 58}, {"source": 39, "target": 50}, {"source": 70, "target": 35}, {"source": 89, "target": 41}, {"source": 54, "target": 24}, {"source": 46, "target": 73}, {"source": 15, "target": 65}, {"source": 77, "target": 48}, {"source": 65, "target": 51}, {"source": 68, "target": 75}, {"source": 19, "target": 4}, {"source": 19, "target": 8}, {"source": 54, "target": 68}, {"source": 30, "target": 54}, {"source": 58, "target": 65}, {"source": 7, "target": 8}, {"source": 46, "target": 61}, {"source": 52, "target": 86}, {"source": 65, "target": 74}, {"source": 80, "target": 60}, {"source": 53, "target": 80}, {"source": 42, "target": 76}, {"source": 17, "target": 40}, {"source": 50, "target": 46}, {"source": 10, "target": 8}, {"source": 3, "target": 5}, {"source": 24, "target": 36}, {"source": 10, "target": 4}, {"source": 8, "target": 10}, {"source": 87, "target": 49}, {"source": 26, "target": 25}, {"source": 77, "target": 65}, {"source": 26, "target": 73}, {"source": 43, "target": 42}, {"source": 14, "target": 19}, {"source": 41, "target": 40}, {"source": 49, "target": 51}, {"source": 18, "target": 10}, {"source": 24, "target": 45}, {"source": 58, "target": 61}, {"source": 41, "target": 34}, {"source": 86, "target": 61}, {"source": 20, "target": 18}, {"source": 27, "target": 49}, {"source": 42, "target": 61}, {"source": 5, "target": 20}, {"source": 70, "target": 30}, {"source": 27, "target": 74}, {"source": 35, "target": 89}, {"source": 74, "target": 65}, {"source": 78, "target": 82}, {"source": 43, "target": 61}, {"source": 13, "target": 9}, {"source": 61, "target": 57}, {"source": 46, "target": 75}, {"source": 10, "target": 15}, {"source": 58, "target": 80}, {"source": 78, "target": 44}, {"source": 70, "target": 80}, {"source": 44, "target": 54}, {"source": 55, "target": 22}, {"source": 58, "target": 49}, {"source": 54, "target": 64}, {"source": 80, "target": 36}, {"source": 74, "target": 42}, {"source": 42, "target": 69}, {"source": 86, "target": 88}, {"source": 40, "target": 85}, {"source": 68, "target": 92}, {"source": 73, "target": 65}, {"source": 77, "target": 44}, {"source": 81, "target": 17}, {"source": 53, "target": 26}, {"source": 37, "target": 30}, {"source": 37, "target": 78}, {"source": 27, "target": 56}, {"source": 26, "target": 83}, {"source": 6, "target": 5}, {"source": 19, "target": 20}, {"source": 69, "target": 87}, {"source": 66, "target": 17}, {"source": 69, "target": 26}, {"source": 40, "target": 73}, {"source": 50, "target": 35}, {"source": 70, "target": 26}, {"source": 30, "target": 26}, {"source": 76, "target": 42}, {"source": 39, "target": 89}, {"source": 14, "target": 21}, {"source": 28, "target": 4}, {"source": 40, "target": 60}, {"source": 51, "target": 27}, {"source": 55, "target": 32}, {"source": 87, "target": 41}, {"source": 92, "target": 40}, {"source": 92, "target": 80}, {"source": 56, "target": 28}, {"source": 47, "target": 65}, {"source": 42, "target": 27}, {"source": 64, "target": 37}, {"source": 16, "target": 19}, {"source": 71, "target": 81}, {"source": 43, "target": 24}, {"source": 76, "target": 90}, {"source": 3, "target": 7}, {"source": 45, "target": 73}, {"source": 22, "target": 78}, {"source": 59, "target": 55}, {"source": 73, "target": 26}, {"source": 65, "target": 67}, {"source": 11, "target": 8}, {"source": 39, "target": 46}, {"source": 11, "target": 4}, {"source": 61, "target": 49}, {"source": 4, "target": 14}, {"source": 69, "target": 79}, {"source": 67, "target": 51}, {"source": 32, "target": 92}, {"source": 76, "target": 87}, {"source": 48, "target": 31}, {"source": 40, "target": 26}, {"source": 61, "target": 65}, {"source": 80, "target": 92}, {"source": 44, "target": 26}, {"source": 25, "target": 87}, {"source": 15, "target": 10}, {"source": 82, "target": 80}, {"source": 28, "target": 42}, {"source": 75, "target": 24}, {"source": 21, "target": 2}, {"source": 87, "target": 74}, {"source": 60, "target": 83}, {"source": 55, "target": 88}, {"source": 55, "target": 24}, {"source": 58, "target": 79}, {"source": 86, "target": 57}, {"source": 80, "target": 68}, {"source": 86, "target": 42}, {"source": 73, "target": 77}, {"source": 49, "target": 45}, {"source": 86, "target": 28}, {"source": 86, "target": 54}, {"source": 86, "target": 67}, {"source": 86, "target": 92}, {"source": 92, "target": 58}, {"source": 62, "target": 26}, {"source": 67, "target": 49}, {"source": 65, "target": 49}, {"source": 84, "target": 17}, {"source": 78, "target": 24}, {"source": 53, "target": 55}, {"source": 41, "target": 69}, {"source": 90, "target": 56}, {"source": 21, "target": 4}, {"source": 78, "target": 30}, {"source": 9, "target": 21}, {"source": 16, "target": 10}, {"source": 64, "target": 45}, {"source": 86, "target": 45}, {"source": 44, "target": 58}, {"source": 80, "target": 89}, {"source": 41, "target": 78}, {"source": 40, "target": 45}, {"source": 38, "target": 35}, {"source": 77, "target": 73}, {"source": 61, "target": 69}, {"source": 87, "target": 40}, {"source": 87, "target": 59}, {"source": 32, "target": 58}, {"source": 68, "target": 78}, {"source": 9, "target": 28}, {"source": 3, "target": 20}, {"source": 21, "target": 7}, {"source": 21, "target": 3}, {"source": 31, "target": 89}, {"source": 42, "target": 47}, {"source": 64, "target": 71}, {"source": 86, "target": 25}, {"source": 32, "target": 88}, {"source": 63, "target": 17}, {"source": 83, "target": 49}, {"source": 47, "target": 33}, {"source": 78, "target": 36}, {"source": 30, "target": 62}, {"source": 14, "target": 16}, {"source": 54, "target": 80}, {"source": 32, "target": 30}, {"source": 30, "target": 92}, {"source": 31, "target": 85}, {"source": 30, "target": 58}, {"source": 26, "target": 37}, {"source": 35, "target": 45}, {"source": 56, "target": 43}, {"source": 78, "target": 83}, {"source": 69, "target": 49}, {"source": 90, "target": 65}, {"source": 14, "target": 12}, {"source": 82, "target": 70}, {"source": 7, "target": 3}, {"source": 8, "target": 11}, {"source": 87, "target": 39}, {"source": 3, "target": 4}, {"source": 75, "target": 26}, {"source": 26, "target": 61}, {"source": 27, "target": 67}, {"source": 39, "target": 30}, {"source": 85, "target": 40}, {"source": 65, "target": 63}, {"source": 63, "target": 42}, {"source": 80, "target": 37}, {"source": 16, "target": 7}, {"source": 15, "target": 18}, {"source": 43, "target": 73}, {"source": 86, "target": 81}, {"source": 39, "target": 73}, {"source": 34, "target": 24}, {"source": 67, "target": 79}, {"source": 71, "target": 51}, {"source": 46, "target": 78}, {"source": 9, "target": 2}, {"source": 44, "target": 49}, {"source": 17, "target": 58}, {"source": 48, "target": 92}, {"source": 81, "target": 38}, {"source": 43, "target": 49}, {"source": 4, "target": 35}, {"source": 69, "target": 57}, {"source": 39, "target": 65}, {"source": 77, "target": 43}, {"source": 88, "target": 17}, {"source": 82, "target": 60}, {"source": 8, "target": 1}, {"source": 44, "target": 61}, {"source": 61, "target": 46}, {"source": 67, "target": 83}, {"source": 45, "target": 68}, {"source": 26, "target": 52}, {"source": 26, "target": 40}, {"source": 69, "target": 25}, {"source": 48, "target": 43}, {"source": 66, "target": 35}, {"source": 82, "target": 83}, {"source": 37, "target": 88}, {"source": 49, "target": 44}, {"source": 78, "target": 56}, {"source": 6, "target": 9}, {"source": 57, "target": 86}, {"source": 44, "target": 69}, {"source": 82, "target": 86}, {"source": 57, "target": 44}, {"source": 22, "target": 53}, {"source": 50, "target": 39}, {"source": 79, "target": 90}, {"source": 67, "target": 30}, {"source": 2, "target": 22}, {"source": 11, "target": 2}, {"source": 89, "target": 43}, {"source": 86, "target": 9}, {"source": 66, "target": 58}, {"source": 9, "target": 50}, {"source": 38, "target": 54}, {"source": 33, "target": 65}, {"source": 39, "target": 51}, {"source": 4, "target": 16}, {"source": 61, "target": 45}, {"source": 51, "target": 49}, {"source": 45, "target": 35}, {"source": 39, "target": 22}, {"source": 69, "target": 66}, {"source": 67, "target": 32}, {"source": 39, "target": 58}, {"source": 25, "target": 49}, {"source": 58, "target": 43}, {"source": 49, "target": 47}, {"source": 26, "target": 82}, {"source": 73, "target": 61}, {"source": 21, "target": 5}, {"source": 16, "target": 1}, {"source": 65, "target": 25}, {"source": 66, "target": 39}, {"source": 50, "target": 68}, {"source": 37, "target": 55}, {"source": 46, "target": 92}, {"source": 40, "target": 65}, {"source": 59, "target": 74}, {"source": 81, "target": 39}, {"source": 86, "target": 87}, {"source": 53, "target": 36}, {"source": 9, "target": 5}, {"source": 81, "target": 71}, {"source": 60, "target": 53}, {"source": 73, "target": 49}, {"source": 44, "target": 78}, {"source": 59, "target": 51}, {"source": 44, "target": 51}, {"source": 40, "target": 37}, {"source": 63, "target": 64}, {"source": 20, "target": 9}, {"source": 33, "target": 69}, {"source": 16, "target": 20}, {"source": 25, "target": 42}, {"source": 65, "target": 61}, {"source": 51, "target": 26}, {"source": 46, "target": 89}, {"source": 2, "target": 10}, {"source": 2, "target": 70}, {"source": 80, "target": 53}, {"source": 75, "target": 32}, {"source": 43, "target": 79}, {"source": 80, "target": 17}, {"source": 62, "target": 58}, {"source": 57, "target": 43}, {"source": 10, "target": 3}, {"source": 19, "target": 7}, {"source": 80, "target": 26}, {"source": 46, "target": 37}, {"source": 42, "target": 57}, {"source": 54, "target": 9}, {"source": 14, "target": 9}, {"source": 67, "target": 77}, {"source": 33, "target": 56}, {"source": 53, "target": 35}, {"source": 27, "target": 59}, {"source": 46, "target": 64}, {"source": 92, "target": 69}, {"source": 65, "target": 64}, {"source": 27, "target": 73}, {"source": 72, "target": 48}, {"source": 66, "target": 48}, {"source": 62, "target": 46}, {"source": 42, "target": 56}, {"source": 59, "target": 87}, {"source": 65, "target": 28}, {"source": 45, "target": 88}, {"source": 45, "target": 9}, {"source": 13, "target": 7}, {"source": 10, "target": 18}, {"source": 86, "target": 83}, {"source": 54, "target": 17}, {"source": 53, "target": 60}, {"source": 92, "target": 78}, {"source": 17, "target": 26}, {"source": 69, "target": 58}, {"source": 42, "target": 65}, {"source": 26, "target": 62}, {"source": 52, "target": 57}, {"source": 2, "target": 26}, {"source": 35, "target": 30}, {"source": 9, "target": 75}, {"source": 78, "target": 92}, {"source": 51, "target": 25}, {"source": 59, "target": 86}, {"source": 69, "target": 31}, {"source": 10, "target": 2}, {"source": 60, "target": 35}, {"source": 17, "target": 9}, {"source": 8, "target": 7}, {"source": 59, "target": 41}, {"source": 49, "target": 67}, {"source": 26, "target": 76}, {"source": 36, "target": 26}, {"source": 8, "target": 3}, {"source": 48, "target": 38}, {"source": 37, "target": 50}, {"source": 47, "target": 59}, {"source": 68, "target": 64}, {"source": 44, "target": 89}, {"source": 39, "target": 81}, {"source": 44, "target": 65}, {"source": 74, "target": 72}, {"source": 40, "target": 81}, {"source": 40, "target": 53}, {"source": 69, "target": 56}, {"source": 88, "target": 32}, {"source": 63, "target": 34}, {"source": 9, "target": 14}]}